zen_markup_lang/__init__.py
zen_markup_lang/lexer.py
zen_markup_lang/zml.py
zen_markup_lang/ply/__init__.py
zen_markup_lang/ply/lex.py
zen_markup_lang/ply/yacc.py
zen_markup_lang-0.1.0.dist-info/LICENSE
zen_markup_lang-0.1.0.dist-info/METADATA
zen_markup_lang-0.1.0.dist-info/WHEEL
zen_markup_lang-0.1.0.dist-info/top_level.txt
zen_markup_lang-0.1.0.dist-info/RECORD
